[
  {
    "slug": "will-trump-visit-china-by-may-15-835-774-595",
    "vol": 15068494.055106035,
    "group": "admit",
    "status": "ok",
    "tape_source": "subgraph",
    "n_fills": 3395,
    "n_directional": 980,
    "gini": 0.825215120331956
  },
  {
    "slug": "megaeth-market-cap-fdv-1pt5b-one-day-after-launch-371-844-879-681",
    "vol": 2176834.897406998,
    "group": "admit",
    "status": "ok",
    "tape_source": "subgraph",
    "n_fills": 3007,
    "n_directional": 1039,
    "gini": 0.8277005022245201
  },
  {
    "slug": "us-escorts-commercial-ship-through-hormuz-by-april-30-894",
    "vol": 1094485.188121001,
    "group": "admit",
    "status": "ok",
    "tape_source": "subgraph",
    "n_fills": 4389,
    "n_directional": 1694,
    "gini": 0.8424353821456256
  },
  {
    "slug": "will-the-indian-national-congress-inc-win-the-most-seats-in-the-2026-tamil-nadu-legislative-assembly-election",
    "vol": 17877969.460003857,
    "group": "split-clean",
    "status": "ok",
    "tape_source": "subgraph",
    "n_fills": 1669,
    "n_directional": 166,
    "gini": 0.7717778313092818
  },
  {
    "slug": "trump-declassifies-new-ufo-files-by-april-30",
    "vol": 249401.28714699997,
    "group": "split-clean",
    "status": "ok",
    "tape_source": "subgraph",
    "n_fills": 1433,
    "n_directional": 671,
    "gini": 0.8110074265650062
  },
  {
    "slug": "will-alfonso-lpez-chau-finish-in-second-place-in-the-first-round-of-the-2026-peruvian-presidential-election",
    "vol": 101196.88722699997,
    "group": "split-clean",
    "status": "ok",
    "tape_source": "subgraph",
    "n_fills": 709,
    "n_directional": 189,
    "gini": 0.7396242025950124
  },
  {
    "slug": "will-carlos-lvarez-finish-in-second-place-in-the-first-round-of-the-2026-peruvian-presidential-election",
    "vol": 95203.05413100004,
    "group": "split-clean",
    "status": "ok",
    "tape_source": "subgraph",
    "n_fills": 880,
    "n_directional": 226,
    "gini": 0.8588417527944563
  },
  {
    "slug": "will-the-freedom-movement-gs-be-part-of-the-next-government-of-slovenia-786",
    "vol": 47205.052398,
    "group": "split-clean",
    "status": "ok",
    "tape_source": "subgraph",
    "n_fills": 426,
    "n_directional": 138,
    "gini": 0.7638008356010297
  }
]